{"name":"iknow_1000_step_05","version":1,"cards":[{"kanji":"問題が一つあります","kana":"もんだいがひとつあります","translation":"There's one problem.","furigana":[0,4,5,2],"kanjiLength":[2,1],"sound":"JS09359A.mp3"},{"kanji":"この問題はかなり易しいです","kana":"このもんだいはかなりやさしいです","translation":"This problem is fairly easy.","furigana":[2,4,10,2],"kanjiLength":[2,1],"sound":"JS09402A.mp3"},{"kanji":"私にはたくさんのお金が必要だ","kana":"わたしにはたくさんのおかねがひつようだ","translation":"I need a lot of money.","furigana":[0,3,11,2,14,4],"kanjiLength":[1,1,2],"sound":"JS07750A.mp3"},{"kanji":"新しい歯ブラシが必要だ","kana":"あたらしいはブラシがひつようだ","translation":"I need a new toothbrush.","furigana":[0,3,5,1,10,4],"kanjiLength":[1,1,2],"sound":"JS07452A.mp3"},{"kanji":"この車はよくもっている","kana":"このくるまはよくもっている","translation":"This car has lasted a long time.","furigana":[2,3],"kanjiLength":[1],"sound":"c5elaochis.mp3"},{"kanji":"彼女はもう長くはもたないだろう","kana":"かのじょはもうながくはもたないだろう","translation":"She won't be able to hold on much longer.","furigana":[0,4,7,2],"kanjiLength":[2,1],"sound":"f55ed8ciak.mp3"},{"kanji":"電車のドアが開きました","kana":"でんしゃのドアがあきました","translation":"The train door opened.","furigana":[0,4,8,1],"kanjiLength":[2,1],"sound":"JS00067A.mp3"},{"kanji":"銀行は3時まで開いています","kana":"ぎんこうはさんじまであいています","translation":"The bank is open until three o'clock.","furigana":[0,4,5,2,7,1,10,1],"kanjiLength":[2,1,1,1],"sound":"JS02364A.mp3"},{"kanji":"昨年は地震が多い年でした","kana":"さくねんはじしんがおおいとしでした","translation":"We had a lot of earthquakes last year.","furigana":[0,4,5,3,9,2,12,2],"kanjiLength":[2,2,1,1],"sound":"JS03392A.mp3"},{"kanji":"私たちは昨年富士山に登りました","kana":"わたしたちはさくねんふじさんにのぼりました","translation":"We climbed Mount Fuji last year.","furigana":[0,3,6,4,10,4,15,2],"kanjiLength":[1,2,3,1],"sound":"JS07110A.mp3"},{"kanji":"けがはもう治りましたか","kana":"けがはもうなおりましたか","translation":"Is your injury cured yet?","furigana":[5,2],"kanjiLength":[1],"sound":"JS06624A.mp3"},{"kanji":"やっと風邪が治りました","kana":"やっとかぜがなおりました","translation":"I've finally recovered from a cold.","furigana":[3,2,6,2],"kanjiLength":[2,1],"sound":"6373chf9qc.mp3"},{"kanji":"この服は300ドルしました","kana":"このふくはさんびゃくドルしました","translation":"These clothes cost 300 dollars.","furigana":[2,2,5,5],"kanjiLength":[1,3],"sound":"JS06571A.mp3"},{"kanji":"全てのシステムが停止した","kana":"すべてのシステムがていしした","translation":"All systems stopped working.","furigana":[0,2,9,3],"kanjiLength":[1,2],"sound":"JS03698A.mp3"},{"kanji":"会社に新しいシステムが入った","kana":"かいしゃにあたらしいシステムがはいった","translation":"A new system has been introduced to the company.","furigana":[0,4,5,3,15,2],"kanjiLength":[2,1,1],"sound":"851f9u70q8.mp3"},{"kanji":"飛行機が1時間以上遅れた","kana":"ひこうきがいちじかんいじょうおくれた","translation":"The plane arrived over an hour late.","furigana":[0,4,5,2,7,3,10,4,14,2],"kanjiLength":[3,1,2,2,1],"sound":"JS00435A.mp3"},{"kanji":"今日は水を2リットル以上飲んだわ","kana":"きょうはみずをにリットルいじょうのんだわ","translation":"I drank more than two liters of water today.","furigana":[0,3,4,2,7,1,12,4,16,1],"kanjiLength":[2,1,1,2,1],"sound":"JS02342A.mp3"},{"kanji":"それは最近話題の本ですね","kana":"それはさいきんわだいのほんですね","translation":"That's the book that people have been talking about lately.","furigana":[3,4,7,3,11,2],"kanjiLength":[2,2,1],"sound":"JS03297A.mp3"},{"kanji":"最近仕事がかなりハードです","kana":"さいきんしごとがかなりハードです","translation":"My work is pretty hard these days.","furigana":[0,4,4,3],"kanjiLength":[2,2],"sound":"JS00966A.mp3"},{"kanji":"私は世界旅行をしたい","kana":"わたしはせかいりょこうをしたい","translation":"I want to travel around the world.","furigana":[0,3,4,3,7,4],"kanjiLength":[1,2,2],"sound":"JS04773A.mp3"},{"kanji":"エベレストは世界でいちばん高い山です","kana":"エベレストはせかいでいちばんたかいやまです","translation":"Mt. Everest is the tallest mountain in the world.","furigana":[6,3,14,2,17,2],"kanjiLength":[2,1,1],"sound":"b3dl9u3af8.mp3"},{"kanji":"新しいコンピューターを買った","kana":"あたらしいコンピューターをかった","translation":"I bought a new computer.","furigana":[0,3,13,1],"kanjiLength":[1,1],"sound":"JS03268A.mp3"},{"kanji":"このコンピューターはすごく遅いです","kana":"このコンピューターはすごくおそいです","translation":"This computer is so slow.","furigana":[13,2],"kanjiLength":[1],"sound":"232m13cp08.mp3"},{"kanji":"犬にえさをやった","kana":"いぬにえさをやった","translation":"I fed the dog.","furigana":[0,2],"kanjiLength":[1],"sound":"JS09463A.mp3"},{"kanji":"毎日金魚に餌をやります","kana":"まいにちきんぎょにえさをやります","translation":"I feed the goldfish everyday.","furigana":[0,4,4,4,9,2],"kanjiLength":[2,2,1],"sound":"JS03545A.mp3"},{"kanji":"それはどういう意味ですか","kana":"それはどういういみですか","translation":"What does it mean?","furigana":[7,2],"kanjiLength":[2],"sound":"JS00582A.mp3"},{"kanji":"この言葉の意味が分かりません","kana":"このことばのいみがわかりません","translation":"I don't understand the meaning of this word.","furigana":[2,3,6,2,9,1],"kanjiLength":[2,2,1],"sound":"JS03172A.mp3"},{"kanji":"この町は人口が増えた","kana":"このまちはじんこうがふえた","translation":"The population in this town has increased.","furigana":[2,2,5,4,10,1],"kanjiLength":[1,2,1],"sound":"JS07973A.mp3"},{"kanji":"日本に住む外国人が増えています","kana":"にほんにすむがいこくじんがふえています","translation":"The number of foreigners living in Japan is increasing.","furigana":[0,3,4,1,6,4,10,2,13,1],"kanjiLength":[2,1,2,1,1],"sound":"JS01351A.mp3"},{"kanji":"良い家を選ぶのは難しい","kana":"よいいえをえらぶのはむずかしい","translation":"It's difficult to choose a good house.","furigana":[0,1,2,2,5,2,10,3],"kanjiLength":[1,1,1,1],"sound":"JS00878A.mp3"},{"kanji":"子供は親を選べません","kana":"こどもはおやをえらべません","translation":"Children cannot choose their parents.","furigana":[0,3,4,2,7,2],"kanjiLength":[2,1,1],"sound":"356885ev1g.mp3"},{"kanji":"日本での生活は楽しいです","kana":"にほんでのせいかつはたのしいです","translation":"Life in Japan is fun.","furigana":[0,3,5,4,10,2],"kanjiLength":[2,2,1],"sound":"JS04673A.mp3"},{"kanji":"彼は海外での生活が長いです","kana":"かれはかいがいでのせいかつがながいです","translation":"He's lived abroad for a long time.","furigana":[0,2,3,4,9,4,14,2],"kanjiLength":[1,2,2,1],"sound":"JS01327A.mp3"},{"kanji":"早く授業を進めましょう","kana":"はやくじゅぎょうをすすめましょう","translation":"Let's hurry and move on with the class.","furigana":[0,2,3,5,9,2],"kanjiLength":[1,2,1],"sound":"JS04570A.mp3"},{"kanji":"話を先に進めてください","kana":"はなしをさきにすすめてください","translation":"Please proceed with the topic (of the conversation).","furigana":[0,3,4,2,7,2],"kanjiLength":[1,1,1],"sound":"341hd01kn4.mp3"},{"kanji":"仕事を続けてください","kana":"しごとをつづけてください","translation":"Please keep working.","furigana":[0,3,4,2],"kanjiLength":[2,1],"sound":"JS05891A.mp3"},{"kanji":"さっきの話を続けましょう","kana":"さっきのはなしをつづけましょう","translation":"Let's continue the conversation we had earlier.","furigana":[4,3,8,2],"kanjiLength":[1,1],"sound":"JS03450A.mp3"},{"kanji":"お金がほとんどありません","kana":"おかねがほとんどありません","translation":"I have little money.","furigana":[1,2],"kanjiLength":[1],"sound":"JS08565A.mp3"},{"kanji":"ここはほとんど変わっていませんね","kana":"ここはほとんどかわっていませんね","translation":"This place has hardly changed.","furigana":[7,1],"kanjiLength":[1],"sound":"94256a0rjg.mp3"},{"kanji":"彼は小さな会社に勤めています","kana":"かれはちいさなかいしゃにつとめています","translation":"He's working at a small business firm.","furigana":[0,2,3,2,7,4,12,2],"kanjiLength":[1,1,2,1],"sound":"JS01360A.mp3"},{"kanji":"明日会社を休みます","kana":"あしたかいしゃをやすみます","translation":"I'm off work tomorrow.","furigana":[0,3,3,4,8,2],"kanjiLength":[2,2,1],"sound":"JS09413A.mp3"},{"kanji":"ここが私の家です","kana":"ここがわたしのいえです","translation":"This is my house.","furigana":[3,3,7,2],"kanjiLength":[1,1],"sound":"JS00354A.mp3"},{"kanji":"昨日の夜は家にいました","kana":"きのうのよるはいえにいました","translation":"I was at home last night.","furigana":[0,3,4,2,7,2],"kanjiLength":[2,1,1],"sound":"JS09743A.mp3"},{"kanji":"毎年多くの人が海外へ旅行する","kana":"まいとしおおくのひとがかいがいへりょこうする","translation":"A lot of people travel abroad every year.","furigana":[0,4,4,2,8,2,11,4,16,4],"kanjiLength":[2,1,1,2,2],"sound":"JS00974A.mp3"},{"kanji":"私はその事故について多くは知りません","kana":"わたしはそのじこについておおくはしりません","translation":"I don't know much about the accident.","furigana":[0,3,6,2,12,2,16,1],"kanjiLength":[1,2,1,1],"sound":"758aet0bp4.mp3"},{"kanji":"あなたの話は面白いね","kana":"あなたのはなしはおもしろいね","translation":"Your story's interesting.","furigana":[4,3,8,4],"kanjiLength":[1,2],"sound":"JS07414A.mp3"},{"kanji":"その話は本当ですか","kana":"そのはなしはほんとうですか","translation":"Is the story true?","furigana":[2,3,6,4],"kanjiLength":[1,2],"sound":"JS08605A.mp3"},{"kanji":"レタスの値段がまた上がりました","kana":"レタスのねだんがまたあがりました","translation":"The price of lettuce has gone up again.","furigana":[4,3,10,1],"kanjiLength":[2,1],"sound":"d56b4t73ec.mp3"},{"kanji":"コーヒーをもう一杯ください","kana":"コーヒーをもういっぱいください","translation":"Please give me another cup of coffee.","furigana":[7,4],"kanjiLength":[2],"sound":"JS09233A.mp3"},{"kanji":"もう一度彼女に会いたいです","kana":"もういちどかのじょにあいたいです","translation":"I want to see her once again.","furigana":[2,2,4,1,5,4,10,1],"kanjiLength":[1,1,2,1],"sound":"b5ed13e43g.mp3"},{"kanji":"弟は切手を集めています","kana":"おとうとはきってをあつめています","translation":"My little brother collects stamps.","furigana":[0,4,5,3,9,2],"kanjiLength":[1,2,1],"sound":"JS00176A.mp3"},{"kanji":"学生たちはインターネットでいろいろな情報を集めた","kana":"がくせいたちはインターネットでいろいろなじょうほうをあつめた","translation":"The students collected all kinds of information on the Internet.","furigana":[0,4,20,5,26,2],"kanjiLength":[2,2,1],"sound":"JS04237A.mp3"},{"kanji":"彼は大きな声で話した","kana":"かれはおおきなこえではなした","translation":"He spoke loudly.","furigana":[0,2,3,2,7,2,10,2],"kanjiLength":[1,1,1,1],"sound":"JS03020A.mp3"},{"kanji":"私たちは大きな声で歌いました","kana":"わたしたちはおおきなこえでうたいました","translation":"We sang loudly.","furigana":[0,3,6,2,10,2,13,2],"kanjiLength":[1,1,1,1],"sound":"JS00702A.mp3"},{"kanji":"東京に来るのは初めてです","kana":"とうきょうにくるのははじめてです","translation":"It's my first time visiting Tokyo.","furigana":[0,5,6,1,10,2],"kanjiLength":[2,1,1],"sound":"JS07301A.mp3"},{"kanji":"彼女は寿司を初めて食べました","kana":"かのじょはすしをはじめてたべました","translation":"She ate sushi for the first time.","furigana":[0,4,5,2,8,2,12,1],"kanjiLength":[2,2,1,1],"sound":"JS04561A.mp3"},{"kanji":"信号が青に変わりました","kana":"しんごうがあおにかわりました","translation":"The traffic light turned green.","furigana":[0,4,5,2,8,1],"kanjiLength":[2,1,1],"sound":"JS01863A.mp3"},{"kanji":"彼はすごく変わった","kana":"かれはすごくかわった","translation":"He's changed a lot.","furigana":[0,2,6,1],"kanjiLength":[1,1],"sound":"e55i5sagds.mp3"},{"kanji":"帰ったらまず手を洗いましょう","kana":"かえったらまずてをあらいましょう","translation":"When you get home, wash your hands first.","furigana":[0,2,7,1,9,2],"kanjiLength":[1,1,1],"sound":"JS08704A.mp3"},{"kanji":"考える前にまずやってみよう","kana":"かんがえるまえにまずやってみよう","translation":"Before you think, try.","furigana":[0,3,5,2],"kanjiLength":[1,1],"sound":"45dke61n1s.mp3"},{"kanji":"これは大きな社会問題になっている","kana":"これはおおきなしゃかいもんだいになっている","translation":"This is a big social problem.","furigana":[3,2,7,4,11,4],"kanjiLength":[1,2,2],"sound":"JS03896A.mp3"},{"kanji":"みんなでより良い社会を作りましょう","kana":"みんなでよりよいしゃかいをつくりましょう","translation":"Let's build a better society together.","furigana":[6,1,8,4,13,2],"kanjiLength":[1,2,1],"sound":"e5dl4j856k.mp3"},{"kanji":"私はその映画のプログラムを買いました","kana":"わたしはそのえいがのプログラムをかいました","translation":"I bought a program booklet of the movie.","furigana":[0,3,6,3,16,1],"kanjiLength":[1,2,1],"sound":"96elcu585k.mp3"},{"kanji":"私にそんな力はありません","kana":"わたしにそんなちからはありません","translation":"I don't have the strength.","furigana":[0,3,7,3],"kanjiLength":[1,1],"sound":"f5484g39bg.mp3"},{"kanji":"彼の声には力がなかった","kana":"かれのこえにはちからがなかった","translation":"There was no strength in his voice.","furigana":[0,2,3,2,7,3],"kanjiLength":[1,1,1],"sound":"14cd6ff5ss.mp3"},{"kanji":"まあ今回は許してあげよう","kana":"まあこんかいはゆるしてあげよう","translation":"Well, I'll let you off this time.","furigana":[2,4,7,2],"kanjiLength":[2,1],"sound":"JS03243A.mp3"},{"kanji":"今回はビジネスクラスに乗りました","kana":"こんかいはビジネスクラスにのりました","translation":"This time I flew business class.","furigana":[0,4,13,1],"kanjiLength":[2,1],"sound":"b43h7u8rsg.mp3"},{"kanji":"今日の予定を教えてください","kana":"きょうのよていをおしえてください","translation":"Please tell me your schedule today.","furigana":[0,3,4,3,8,2],"kanjiLength":[2,2,1],"sound":"JS09706A.mp3"},{"kanji":"カレンダーに予定を書いた","kana":"カレンダーによていをかいた","translation":"I wrote my schedule on the calendar.","furigana":[6,3,10,1],"kanjiLength":[2,1],"sound":"JS01842A.mp3"},{"kanji":"電気が付いたままですよ","kana":"でんきがついたままですよ","translation":"The light is still on.","furigana":[0,3,4,1],"kanjiLength":[2,1],"sound":"JS08794A.mp3"},{"kanji":"そのままのあなたでいてください","kana":"そのままのあなたでいてください","translation":"Please stay as you are.","furigana":[],"kanjiLength":[],"sound":"355oeia8mg.mp3"},{"kanji":"私はテレビをあまり見ません","kana":"わたしはテレビをあまりみません","translation":"I don't watch much TV.","furigana":[0,3,11,1],"kanjiLength":[1,1],"sound":"JS06129A.mp3"},{"kanji":"テレビのチャンネルを変えてください","kana":"テレビのチャンネルをかえてください","translation":"Please change the TV channel.","furigana":[10,1],"kanjiLength":[1],"sound":"JS05637A.mp3"},{"kanji":"体重がかなり減りました","kana":"たいじゅうがかなりへりました","translation":"I've lost a lot of weight.","furigana":[0,5,9,1],"kanjiLength":[2,1],"sound":"JS08337A.mp3"},{"kanji":"最近子供の数が減っている","kana":"さいきんこどものかずがへっている","translation":"Lately, there have been fewer children.","furigana":[0,4,4,3,8,2,11,1],"kanjiLength":[2,2,1,1],"sound":"123kd11b9g.mp3"},{"kanji":"突然電気が消えた","kana":"とつぜんでんきがきえた","translation":"Suddenly the lights went out.","furigana":[0,4,4,3,8,1],"kanjiLength":[2,2,1],"sound":"JS01988A.mp3"},{"kanji":"私はもう消えてしまいたい","kana":"わたしはもうきえてしまいたい","translation":"I want to disappear now.","furigana":[0,3,6,1],"kanjiLength":[1,1],"sound":"b64ka741r4.mp3"},{"kanji":"うちは五人家族です","kana":"うちはごにんかぞくです","translation":"We're a family of five.","furigana":[3,1,4,2,6,3],"kanjiLength":[1,1,2],"sound":"JS01624A.mp3"},{"kanji":"私は家族を愛しています","kana":"わたしはかぞくをあいしています","translation":"I love my family.","furigana":[0,3,4,3,8,2],"kanjiLength":[1,2,1],"sound":"JS00011A.mp3"},{"kanji":"今月と先月の売上を比べた","kana":"こんげつとせんげつのうりあげをくらべた","translation":"I compared this month's sales with last month's.","furigana":[0,4,5,4,10,4,15,2],"kanjiLength":[2,2,2,1],"sound":"JS02532A.mp3"},{"kanji":"ニューヨークと比べて東京はどうですか","kana":"ニューヨークとくらべてとうきょうはどうですか","translation":"How is Tokyo compared to New York?","furigana":[7,2,11,5],"kanjiLength":[1,2],"sound":"059s3h8t34.mp3"},{"kanji":"祖母は京都で生まれました","kana":"そぼはきょうとでうまれました","translation":"My grandmother was born in Kyoto.","furigana":[0,2,3,4,8,1],"kanjiLength":[2,2,1],"sound":"JS05094A.mp3"},{"kanji":"この温泉はただです","kana":"このおんせんはただです","translation":"This hot spring bathhouse is free.","furigana":[2,4],"kanjiLength":[2],"sound":"JS05344A.mp3"},{"kanji":"今日ただでノートをもらった","kana":"きょうただでノートをもらった","translation":"Today I got a notebook free.","furigana":[0,3],"kanjiLength":[2],"sound":"944b9l114g.mp3"},{"kanji":"これらの質問に全部答えてください","kana":"これらのしつもんにぜんぶこたえてください","translation":"Please answer all these questions.","furigana":[4,4,9,3,12,2],"kanjiLength":[2,2,1],"sound":"734c299p1s.mp3"},{"kanji":"この単語の意味を辞書で調べましょう","kana":"このたんごのいみをじしょでしらべましょう","translation":"Let's look up the meaning of this word in a dictionary.","furigana":[2,3,6,2,9,3,13,2],"kanjiLength":[2,2,2,1],"sound":"JS04330A.mp3"},{"kanji":"日本の社会問題をネットで調べました","kana":"にほんのしゃかいもんだいをネットでしらべました","translation":"I looked into issues in Japanese society on the Internet.","furigana":[0,3,4,4,8,4,17,2],"kanjiLength":[2,2,2,1],"sound":"55crd13fjc.mp3"},{"kanji":"彼は事故で怪我をしました","kana":"かれはじこでけがをしました","translation":"He was injured in the accident.","furigana":[0,2,3,2,6,2],"kanjiLength":[1,2,2],"sound":"JS03656A.mp3"},{"kanji":"今朝事故で電車が止まりました","kana":"けさじこででんしゃがとまりました","translation":"The train stopped this morning due to an accident.","furigana":[0,2,2,2,5,4,10,1],"kanjiLength":[2,2,2,1],"sound":"JS06502A.mp3"},{"kanji":"あとで電話します","kana":"あとででんわします","translation":"I will call you later.","furigana":[3,3],"kanjiLength":[2],"sound":"JS06190A.mp3?1216574220"},{"kanji":"私は毎週母に電話をします","kana":"わたしはまいしゅうははにでんわをします","translation":"I call my mother every week.","furigana":[0,3,4,5,9,2,12,3],"kanjiLength":[1,2,1,2],"sound":"JS08635A.mp3"},{"kanji":"母はまだ外国に行ったことがありません","kana":"はははまだがいこくにいったことがありません","translation":"My mother has never been abroad.","furigana":[0,2,5,4,10,1],"kanjiLength":[1,2,1],"sound":"JS01349A.mp3"},{"kanji":"私は外国に住みたいです","kana":"わたしはがいこくにすみたいです","translation":"I want to live in a foreign country.","furigana":[0,3,4,4,9,1],"kanjiLength":[1,2,1],"sound":"c51b0600ts.mp3"},{"kanji":"銀行は3時まで開いています","kana":"ぎんこうはさんじまであいています","translation":"The bank is open until three o'clock.","furigana":[0,4,5,2,7,1,10,1],"kanjiLength":[2,1,1,1],"sound":"JS02364A.mp3"},{"kanji":"姉は銀行で働いています","kana":"あねはぎんこうではたらいています","translation":"My big sister works at a bank.","furigana":[0,2,3,4,8,3],"kanjiLength":[1,2,1],"sound":"JS07338A.mp3"},{"kanji":"お金はまだ十分あります","kana":"おかねはまだじゅうぶんあります","translation":"We still have plenty of money.","furigana":[1,2,6,5],"kanjiLength":[1,2],"sound":"JS04012A.mp3"},{"kanji":"ディズニーランドは大人でも十分楽しめます","kana":"ディズニーランドはおとなでもじゅうぶんたのしめます","translation":"Even adults can fully enjoy Disney Land.","furigana":[9,3,14,5,19,2],"kanjiLength":[2,2,1],"sound":"240d3nbsek.mp3"},{"kanji":"このビールはあまり美味しくありません","kana":"このビールはあまりおいしくありません","translation":"This beer isn't very good.","furigana":[9,2],"kanjiLength":[2],"sound":"JS00230A.mp3"},{"kanji":"私はテレビをあまり見ません","kana":"わたしはテレビをあまりみません","translation":"I don't watch TV that much.","furigana":[0,3,11,1],"kanjiLength":[1,1],"sound":"JS06129A.mp3"},{"kanji":"その写真を見せてください","kana":"そのしゃしんをみせてください","translation":"Please show me the picture.","furigana":[2,4,7,1],"kanjiLength":[2,1],"sound":"JS08911A.mp3"},{"kanji":"バラにはいろいろな種類があります","kana":"バラにはいろいろなしゅるいがあります","translation":"There are various types of rose.","furigana":[9,4],"kanjiLength":[2],"sound":"JS04095A.mp3"},{"kanji":"あのレストランはワインの種類が少ないです","kana":"あのレストランはワインのしゅるいがすくないです","translation":"That restaurant has only a few types of wine.","furigana":[12,4,17,2],"kanjiLength":[2,1],"sound":"2i857aclk.mp3"},{"kanji":"あなたの意見が聞きたいです","kana":"あなたのいけんがききたいです","translation":"I want to hear your opinion.","furigana":[4,3,8,1],"kanjiLength":[2,1],"sound":"JS00406A.mp3"},{"kanji":"彼は人の意見を聞かない","kana":"かれはひとのいけんをきかない","translation":"He doesn't listen to others' opinions.","furigana":[0,2,3,2,6,3,10,1],"kanjiLength":[1,1,2,1],"sound":"e52gc6dgcs.mp3"},{"kanji":"今日の新聞どこに置いた","kana":"きょうのしんぶんどこにおいた","translation":"Where did you put today's newspaper?","furigana":[0,3,4,4,11,1],"kanjiLength":[2,2,1],"sound":"JS04439A.mp3"},{"kanji":"私は毎朝電車で新聞を読みます","kana":"わたしはまいあさでんしゃでしんぶんをよみます","translation":"I read the newspaper on the train every morning.","furigana":[0,3,4,4,8,4,13,4,18,1],"kanjiLength":[1,2,2,2,1],"sound":"46723l1cbs.mp3"},{"kanji":"彼は文章がとてもうまい","kana":"かれはぶんしょうがとてもうまい","translation":"His writing is very good.","furigana":[0,2,3,5],"kanjiLength":[1,2],"sound":"JS08253A.mp3"},{"kanji":"この文章の意味が分かりません","kana":"このぶんしょうのいみがわかりません","translation":"I don't understand the meaning of this sentence.","furigana":[2,5,8,2,11,1],"kanjiLength":[2,2,1],"sound":"85398q8gvc.mp3"},{"kanji":"彼女の大きな帽子はとても目立つ","kana":"かのじょのおおきなぼうしはとてもめだつ","translation":"Her big hat really stands out.","furigana":[0,4,5,2,9,3,16,2],"kanjiLength":[2,1,2,2],"sound":"JS09198A.mp3"},{"kanji":"彼はクラスで目立っている","kana":"かれはクラスでめだっている","translation":"He stands out in the class.","furigana":[0,2,7,2],"kanjiLength":[1,2],"sound":"b5ee8oa8oo.mp3"},{"kanji":"試合の相手は誰ですか","kana":"しあいのあいてはだれですか","translation":"Who are they playing against?","furigana":[0,3,4,3,8,2],"kanjiLength":[2,2,1],"sound":"JS00018A.mp3"},{"kanji":"相手は何て言ってますか","kana":"あいてはなんていってますか","translation":"What does the other party say?","furigana":[0,3,4,2,7,1],"kanjiLength":[2,1,1],"sound":"15295i7ajo.mp3"},{"kanji":"病院はどこですか","kana":"びょういんはどこですか","translation":"Where is the hospital?","furigana":[0,5],"kanjiLength":[2],"sound":"JS07847A.mp3"},{"kanji":"あの病院はお医者さんの数が少ないです","kana":"あのびょういんはおいしゃさんのかずがすくないです","translation":"That hospital has only a few doctors.","furigana":[2,5,9,3,15,2,18,2],"kanjiLength":[2,2,1,1],"sound":"86e98p1ln4.mp3"},{"kanji":"その辞書はとても厚い","kana":"そのじしょはとてもあつい","translation":"That dictionary is very thick.","furigana":[2,3,9,2],"kanjiLength":[2,1],"sound":"JS00156A.mp3"},{"kanji":"私はあのお店の厚いステーキが大好きだ","kana":"わたしはあのおみせのあついステーキがだいすきだ","translation":"I love the thick steak at that restaurant.","furigana":[0,3,7,2,10,2,18,3],"kanjiLength":[1,1,1,2],"sound":"64e7ba5h78.mp3"},{"kanji":"忙しいので手伝ってください","kana":"いそがしいのでてつだってください","translation":"I have a lot to do, so please help me.","furigana":[0,3,7,3],"kanjiLength":[1,2],"sound":"JS00452A.mp3"},{"kanji":"3月は仕事が忙しい","kana":"さんがつはしごとがいそがしい","translation":"I'm busy at work in March.","furigana":[0,2,2,2,5,3,9,3],"kanjiLength":[1,1,2,1],"sound":"JS03665A.mp3"},{"kanji":"この電子辞書はとても薄い","kana":"このでんしじしょはとてもうすい","translation":"This electronic dictionary is very thin.","furigana":[2,3,5,3,12,2],"kanjiLength":[2,2,1],"sound":"JS00689A.mp3"},{"kanji":"この料理は味が薄い","kana":"このりょうりはあじがうすい","translation":"This food is tasteless.","furigana":[2,4,7,2,10,2],"kanjiLength":[2,1,1],"sound":"JS00115A.mp3"},{"kanji":"小さな川を渡りました","kana":"ちいさなかわをわたりました","translation":"I crossed a small stream.","furigana":[0,2,4,2,7,2],"kanjiLength":[1,1,1],"sound":"JS01845A.mp3"},{"kanji":"この川は浅いです","kana":"このかわはあさいです","translation":"This river is shallow.","furigana":[2,2,5,2],"kanjiLength":[1,1],"sound":"JS00103A.mp3"},{"kanji":"東の空が暗いです","kana":"ひがしのそらがくらいです","translation":"The sky in the east is dark.","furigana":[0,3,4,2,7,2],"kanjiLength":[1,1,1],"sound":"JS02521A.mp3"},{"kanji":"この部屋は少し暗いですね","kana":"このへやはすこしくらいですね","translation":"It's a little dark in this room.","furigana":[2,2,5,2,8,2],"kanjiLength":[2,1,1],"sound":"14f82raveg.mp3"},{"kanji":"彼はクラスで一番背が高い","kana":"かれはクラスでいちばんせがたかい","translation":"He's the tallest in class.","furigana":[0,2,7,4,11,1,13,2],"kanjiLength":[1,2,1,1],"sound":"JS00494A.mp3?1219919352"},{"kanji":"彼女は黒いドレスを着ています","kana":"かのじょはくろいドレスをきています","translation":"She's wearing a black dress.","furigana":[0,4,5,2,12,1],"kanjiLength":[2,1,1],"sound":"JS02563A.mp3"},{"kanji":"私は黒いバッグを持っています","kana":"わたしはくろいバッグをもっています","translation":"I have a black bag.","furigana":[0,3,4,2,11,1],"kanjiLength":[1,1,1],"sound":"JS07365A.mp3"},{"kanji":"バスで行こう","kana":"バスでいこう","translation":"Let's go by bus.","furigana":[3,1],"kanjiLength":[1],"sound":"JS07312A.mp3"},{"kanji":"ここの海はとても青い","kana":"ここのうみはとてもあおい","translation":"The sea here is very blue.","furigana":[3,2,9,2],"kanjiLength":[1,1],"sound":"JS00034A.mp3"},{"kanji":"彼女は青い目をしています","kana":"かのじょはあおいめをしています","translation":"She has blue eyes.","furigana":[0,4,5,2,8,1],"kanjiLength":[2,1,1],"sound":"JS09133A.mp3"},{"kanji":"この薬を必ず飲んでください","kana":"このくすりをかならずのんでください","translation":"Please be sure to take this medicine.","furigana":[2,3,6,3,10,1],"kanjiLength":[1,1,1],"sound":"JS02445A.mp3"},{"kanji":"昼ご飯の前に薬を飲みました","kana":"ひるごはんのまえにくすりをのみました","translation":"I took medicine before lunch.","furigana":[0,2,3,2,6,2,9,3,13,1],"kanjiLength":[1,1,1,1,1],"sound":"25e0bi34n4.mp3"},{"kanji":"コーヒーに砂糖は入れますか","kana":"コーヒーにさとうはいれますか","translation":"Do you want sugar in your coffee?","furigana":[5,3,9,1],"kanjiLength":[2,1],"sound":"JS03468A.mp3"},{"kanji":"このコーヒーには砂糖が入っていません","kana":"このコーヒーにはさとうがはいっていません","translation":"There is no sugar in this coffee.","furigana":[8,3,12,2],"kanjiLength":[2,1],"sound":"45ff8fd2m8.mp3"},{"kanji":"今日は休みです","kana":"きょうはやすみです","translation":"Today is a holiday.","furigana":[0,3,4,2],"kanjiLength":[2,1],"sound":"JS09412A.mp3"},{"kanji":"木曜日は仕事が休みです","kana":"もくようびはしごとがやすみです","translation":"I'm off on Thursday.","furigana":[0,5,6,3,10,2],"kanjiLength":[3,2,1],"sound":"JS09267A.mp3"},{"kanji":"郵便局はどこですか","kana":"ゆうびんきょくはどこですか","translation":"Where's the post office?","furigana":[0,7],"kanjiLength":[3],"sound":"JS09514A.mp3"},{"kanji":"郵便局で切手を買いました","kana":"ゆうびんきょくできってをかいました","translation":"I bought a stamp at the post office.","furigana":[0,7,8,3,12,1],"kanjiLength":[3,2,1],"sound":"JS01429A.mp3"},{"kanji":"この住所に行ってください","kana":"このじゅうしょにいってください","translation":"Please go to this address.","furigana":[2,5,8,1],"kanjiLength":[2,1],"sound":"JS03977A.mp3"},{"kanji":"ここに住所と氏名を書いてください","kana":"ここにじゅうしょとしめいをかいてください","translation":"Please write your name and address here.","furigana":[3,5,9,3,13,1],"kanjiLength":[2,2,1],"sound":"JS03867A.mp3"},{"kanji":"受付はこちらです","kana":"うけつけはこちらです","translation":"The reception desk is this way.","furigana":[0,4],"kanjiLength":[2],"sound":"JS03139A.mp3"},{"kanji":"こちらへどうぞ","kana":"こちらへどうぞ","translation":"This way please.","furigana":[],"kanjiLength":[],"sound":"JS06282A.mp3"},{"kanji":"会社に財布を忘れた","kana":"かいしゃにさいふをわすれた","translation":"I left my wallet at the office.","furigana":[0,4,5,3,9,2],"kanjiLength":[2,2,1],"sound":"JS03339A.mp3"},{"kanji":"財布は机の下にあった","kana":"さいふはつくえのしたにあった","translation":"My purse was under the desk.","furigana":[0,3,4,3,8,2],"kanjiLength":[2,1,1],"sound":"JS03714A.mp3"},{"kanji":"パスポートが見つからない","kana":"パスポートがみつからない","translation":"I can't find my passport.","furigana":[6,1],"kanjiLength":[1],"sound":"JS07317A.mp3"},{"kanji":"私のパスポートがありません","kana":"わたしのパスポートがありません","translation":"My passport is missing.","furigana":[0,3],"kanjiLength":[1],"sound":"94e6a470gc.mp3"},{"kanji":"そのお年寄りは椅子に座った","kana":"そのおとしよりはいすにすわった","translation":"The old person sat on a chair.","furigana":[3,3,8,2,11,2],"kanjiLength":[2,2,1],"sound":"JS00442A.mp3"},{"kanji":"その椅子を持ってきてください","kana":"そのいすをもってきてください","translation":"Please bring the chair.","furigana":[2,2,5,1],"kanjiLength":[2,1],"sound":"JS09297A.mp3"},{"kanji":"彼女の赤ちゃんは可愛いです","kana":"かのじょのあかちゃんはかわいいです","translation":"Her baby is cute.","furigana":[0,4,5,2,11,3],"kanjiLength":[2,1,2],"sound":"JS01849A.mp3"},{"kanji":"娘に可愛いドレスを着せた","kana":"むすめにかわいいドレスをきせた","translation":"I dressed my daughter in a cute dress.","furigana":[0,3,4,3,12,1],"kanjiLength":[1,2,1],"sound":"JS02079A.mp3"},{"kanji":"私のお祖父さんは毎日散歩します","kana":"わたしのおじいさんはまいにちさんぽします","translation":"My grandpa takes a walk every day.","furigana":[0,3,5,2,10,4,14,3],"kanjiLength":[1,2,2,2],"sound":"JS01073A.mp3"},{"kanji":"私のお祖父さんは北海道に住んでいます","kana":"わたしのおじいさんはほっかいどうにすんでいます","translation":"My grandfather lives in Hokkaido.","furigana":[0,3,5,2,10,6,17,1],"kanjiLength":[1,2,3,1],"sound":"f649dtfnls.mp3"},{"kanji":"ここに切手を貼ってください","kana":"ここにきってをはってください","translation":"Please put a stamp here.","furigana":[3,3,7,1],"kanjiLength":[2,1],"sound":"JS02117A.mp3"},{"kanji":"弟は切手を集めています","kana":"おとうとはきってをあつめています","translation":"My little brother collects stamps.","furigana":[0,4,5,3,9,2],"kanjiLength":[1,2,1],"sound":"JS00176A.mp3"},{"kanji":"夕方は涼しくなりますよ","kana":"ゆうがたはすずしくなりますよ","translation":"It gets cooler in the evening.","furigana":[0,4,5,2],"kanjiLength":[2,1],"sound":"JS04566A.mp3"},{"kanji":"今日はすごく涼しいですね","kana":"きょうはすごくすずしいですね","translation":"It's very cool today.","furigana":[0,3,7,2],"kanjiLength":[2,1],"sound":"92arauc8l0.mp3"},{"kanji":"娘さんはいくつになりましたか","kana":"むすめさんはいくつになりましたか","translation":"How old is your daughter now?","furigana":[0,3],"kanjiLength":[1],"sound":"JS00396A.mp3"},{"kanji":"日本語の単語をいくつ知っていますか","kana":"にほんごのたんごをいくつしっていますか","translation":"How many Japanese words do you know?","furigana":[0,3,3,1,5,3,12,1],"kanjiLength":[2,1,2,1],"sound":"JS00378A.mp3"},{"kanji":"メニューをください","kana":"メニューをください","translation":"Can I have a menu, please?","furigana":[],"kanjiLength":[],"sound":"JS09211A.mp3"},{"kanji":"キッズメニューはありますか","kana":"キッズメニューはありますか","translation":"Do you have a kids menu?","furigana":[],"kanjiLength":[],"sound":"a56e5h7vos.mp3"},{"kanji":"電気をつけてもらえる","kana":"でんきをつけてもらえる","translation":"Can you turn on the light?","furigana":[0,3],"kanjiLength":[2],"sound":"JS06145A.mp3"},{"kanji":"部屋の電気が付いています","kana":"へやのでんきがついています","translation":"The room light is on.","furigana":[0,2,3,3,7,1],"kanjiLength":[2,2,1],"sound":"JS05852A.mp3"},{"kanji":"今日はヤンキースが勝った","kana":"きょうはヤンキースがかった","translation":"The Yankees won today.","furigana":[0,3,10,1],"kanjiLength":[2,1],"sound":"JS01669A.mp3"},{"kanji":"誰も彼には勝てません","kana":"だれもかれにはかてません","translation":"Nobody can win against him.","furigana":[0,2,3,2,7,1],"kanjiLength":[1,1,1],"sound":"355cd91a30.mp3"},{"kanji":"私たちのチームはその試合で負けた","kana":"わたしたちのチームはそのしあいでまけた","translation":"Our team lost the game.","furigana":[0,3,12,3,16,1],"kanjiLength":[1,2,1],"sound":"JS08680A.mp3"},{"kanji":"昨日はドジャースが負けました","kana":"きのうはドジャースがまけました","translation":"Yesterday, the Dodgers lost.","furigana":[0,3,10,1],"kanjiLength":[2,1],"sound":"f466f61rqs.mp3"},{"kanji":"私たちは来年家を建てます","kana":"わたしたちはらいねんいえをたてます","translation":"We'll build a house next year.","furigana":[0,3,6,4,10,2,13,1],"kanjiLength":[1,2,1,1],"sound":"JS05410A.mp3"},{"kanji":"これは父が建てた家です","kana":"これはちちがたてたいえです","translation":"This is the house that my father built.","furigana":[3,2,6,1,9,2],"kanjiLength":[1,1,1],"sound":"239m958aqk.mp3"},{"kanji":"私は毎日日記をつけています","kana":"わたしはまいにちにっきをつけています","translation":"I keep a diary every day.","furigana":[0,3,4,4,8,3],"kanjiLength":[1,2,2],"sound":"JS06851A.mp3"},{"kanji":"姉は毎晩日記を書いています","kana":"あねはまいばんにっきをかいています","translation":"My older sister writes in her diary every evening.","furigana":[0,2,3,4,7,3,11,1],"kanjiLength":[1,2,2,1],"sound":"JS08643A.mp3"},{"kanji":"あのお巡りさんに道を聞きましょう","kana":"あのおまわりさんにみちをききましょう","translation":"Let's ask that police officer for directions.","furigana":[3,2,9,2,12,1],"kanjiLength":[1,1,1],"sound":"JS01189A.mp3"},{"kanji":"私はお巡りさんになりたかった","kana":"わたしはおまわりさんになりたかった","translation":"I wanted to be a police officer.","furigana":[0,3,5,2],"kanjiLength":[1,1],"sound":"36b89q3hds.mp3"},{"kanji":"目覚まし時計を6時にセットした","kana":"めざましどけいをろくじにセットした","translation":"I set my alarm clock at six.","furigana":[0,2,4,3,8,2,10,1],"kanjiLength":[2,2,1,1],"sound":"75efbs473c.mp3"},{"kanji":"レシートを財布に入れました","kana":"レシートをさいふにいれました","translation":"I put the receipt in my wallet.","furigana":[5,3,9,1],"kanjiLength":[2,1],"sound":"JS09927A.mp3"},{"kanji":"レシートを見せてください","kana":"レシートをみせてください","translation":"Please show me the receipt.","furigana":[5,1],"kanjiLength":[1],"sound":"0415859lro.mp3"},{"kanji":"ティッシュを取ってください","kana":"ティッシュをとってください","translation":"Please pass me the tissues.","furigana":[6,1],"kanjiLength":[1],"sound":"JS06014A.mp3"},{"kanji":"駅前でティッシュをもらった","kana":"えきまえでティッシュをもらった","translation":"I received tissue packs in front of the station.","furigana":[0,2,2,2],"kanjiLength":[1,1],"sound":"468gei411c.mp3"},{"kanji":"新しい歯ブラシが必要だ","kana":"あたらしいはブラシがひつようだ","translation":"I need a new toothbrush.","furigana":[0,3,5,1,10,4],"kanjiLength":[1,1,2],"sound":"JS07452A.mp3"},{"kanji":"この歯ブラシは子供のです","kana":"このはブラシはこどものです","translation":"This toothbrush is for kids.","furigana":[2,1,7,3],"kanjiLength":[1,2],"sound":"94bs0iad5s.mp3"},{"kanji":"そこの階段を下りてください","kana":"そこのかいだんをおりてください","translation":"Please go down those stairs.","furigana":[3,4,8,1],"kanjiLength":[2,1],"sound":"JS01250A.mp3"},{"kanji":"ネコが木から下りてきた","kana":"ネコがきからおりてきた","translation":"A cat came down from the tree.","furigana":[3,1,6,1],"kanjiLength":[1,1],"sound":"54ec5cca20.mp3"},{"kanji":"早く顔を洗いなさい","kana":"はやくかおをあらいなさい","translation":"Hurry and wash your face.","furigana":[0,2,3,2,6,2],"kanjiLength":[1,1,1],"sound":"JS00260A.mp3"},{"kanji":"石鹸で手を洗ってください","kana":"せっけんでてをあらってください","translation":"Please wash your hands with soap.","furigana":[0,4,5,1,7,2],"kanjiLength":[2,1,1],"sound":"JS04804A.mp3"},{"kanji":"彼女はパートで働いています","kana":"かのじょはパートではたらいています","translation":"She is working part time.","furigana":[0,4,9,3],"kanjiLength":[2,1],"sound":"el3l8n2jk47ik.mp3"},{"kanji":"妻がパートの仕事を探しています","kana":"つまがパートのしごとをさがしています","translation":"My wife is looking for a part-time job.","furigana":[0,2,7,3,11,2],"kanjiLength":[1,2,1],"sound":"e58f4kb2rs.mp3"}]}